visitors/helpers.py
visitors/visitors.py
visitors/__init__.py
visitors/base.py
visitors/ext/visitors.py
visitors/ext/__init__.py
visitors/ext/pyast.py
visitors/ext/etree.py
visitors/ext/nx.py
visitors/ext/legal.py
visitors-0.1.dist-info/RECORD
visitors-0.1.dist-info/METADATA
visitors-0.1.dist-info/metadata.json
visitors-0.1.dist-info/WHEEL
visitors-0.1.dist-info/DESCRIPTION.rst
visitors-0.1.dist-info/top_level.txt
tests/__init__.py
