Metadata-Version: 2.0
Name: visitors
Version: 0.1
Summary: Basic visitor pattern implementation and extensions
Home-page: http://github.com/twneale/visitors/
Author: Thom Neale
Author-email: twneale@gmail.com
License: BSD
Platform: any
